fsc/hdf5_io/__init__.py
fsc/hdf5_io/_base_classes.py
fsc/hdf5_io/_save_load.py
fsc/hdf5_io/_simple_mapping.py
fsc/hdf5_io/_special_types.py
fsc/hdf5_io/_subscribe.py
fsc/hdf5_io/_sympy_load.py
fsc/hdf5_io/_sympy_save.py
fsc/hdf5_io/_utils.py
fsc/hdf5_io/_version.py
fsc/hdf5_io/version.txt
fsc.hdf5_io-1.0.3.dist-info/AUTHORS
fsc.hdf5_io-1.0.3.dist-info/METADATA
fsc.hdf5_io-1.0.3.dist-info/WHEEL
fsc.hdf5_io-1.0.3.dist-info/entry_points.txt
fsc.hdf5_io-1.0.3.dist-info/top_level.txt
fsc.hdf5_io-1.0.3.dist-info/RECORD
